shangshanhui_test/__init__.py
shangshanhui_test-0.0.2.dist-info/METADATA
shangshanhui_test-0.0.2.dist-info/WHEEL
shangshanhui_test-0.0.2.dist-info/top_level.txt
shangshanhui_test-0.0.2.dist-info/RECORD
