Metadata-Version: 2.1
Name: shangshanhui-test
Version: 0.0.2
Summary: 吃枣药丸
Home-page: UNKNOWN
Author: huiliyi
Author-email: 1900010748@pku.edu.cn
License: UNKNOWN
Platform: UNKNOWN
Requires-Dist: hdmap-base
